arches_modular_reports/__init__.py
arches_modular_reports/admin.py
arches_modular_reports/apps.py
arches_modular_reports/arches_modular_reports_urls.py
arches_modular_reports/celery.py
arches_modular_reports/hosts.py
arches_modular_reports/models.py
arches_modular_reports/settings.py
arches_modular_reports/urls.py
arches_modular_reports/utils.py
arches_modular_reports/wsgi.py
arches_modular_reports/app/utils/decorators.py
arches_modular_reports/app/utils/nodegroup_tile_data_utils.py
arches_modular_reports/app/utils/update_report_configuration_for_nodegroup_permissions.py
arches_modular_reports/app/views/modular_report.py
arches_modular_reports/locale/.gitkeep
arches_modular_reports/media/css/themes/_project.scss
arches_modular_reports/media/img/favicon.png
arches_modular_reports/media/js/reports/modular-report.js
arches_modular_reports/migrations/0001_initial.py
arches_modular_reports/migrations/0002_add_modular_report.py
arches_modular_reports/migrations/0004_handle_for_concept_label_subregions.py
arches_modular_reports/migrations/0005_limit_graph_choices_by_version.py
arches_modular_reports/migrations/0006_improve_report_config_related_name.py
arches_modular_reports/migrations/0007_reportconfig_slug.py
arches_modular_reports/migrations/__init__.py
arches_modular_reports/src/arches_modular_reports/constants.ts
arches_modular_reports/src/arches_modular_reports/declarations.d.ts
arches_modular_reports/src/arches_modular_reports/ModularReport/ModularReport.vue
arches_modular_reports/src/arches_modular_reports/ModularReport/api.ts
arches_modular_reports/src/arches_modular_reports/ModularReport/types.ts
arches_modular_reports/src/arches_modular_reports/ModularReport/utils.ts
arches_modular_reports/src/arches_modular_reports/ModularReport/components/ChildTile.vue
arches_modular_reports/src/arches_modular_reports/ModularReport/components/ChildTileNodeValue.vue
arches_modular_reports/src/arches_modular_reports/ModularReport/components/DataSection.vue
arches_modular_reports-1.0.0b2.dist-info/licenses/LICENSE
arches_modular_reports-1.0.0b2.dist-info/METADATA
arches_modular_reports-1.0.0b2.dist-info/WHEEL
arches_modular_reports-1.0.0b2.dist-info/top_level.txt
arches_modular_reports-1.0.0b2.dist-info/RECORD
