Metadata-Version: 2.4
Name: arches-modular-reports
Version: 1.0.0b2
Summary: Fast, configurable reports for Arches models in Vue.js
Author: Arches Project
License-Expression: AGPL-3.0-or-later
Project-URL: Homepage, https://archesproject.org/
Project-URL: Documentation, https://arches.readthedocs.io
Project-URL: Repository, https://github.com/archesproject/arches-modular-reports.git
Project-URL: Issues, https://github.com/archesproject/arches-modular-reports/issues
Classifier: Development Status :: 4 - Beta
Classifier: Programming Language :: Python
Classifier: Programming Language :: Python :: 3
Classifier: Programming Language :: Python :: 3 :: Only
Classifier: Programming Language :: Python :: 3.10
Classifier: Programming Language :: Python :: 3.11
Classifier: Programming Language :: Python :: 3.12
Classifier: Programming Language :: Python :: 3.13
Classifier: Framework :: Django
Classifier: Framework :: Django :: 4.2
Classifier: Framework :: Django :: 5.2
Classifier: Intended Audience :: Developers
Classifier: Intended Audience :: Science/Research
Classifier: Intended Audience :: Information Technology
Requires-Python: >=3.10
License-File: LICENSE
Requires-Dist: arches<8.2.0,>=7.6.19
Requires-Dist: arches-component-lab>=0.0.1a3
Dynamic: license-file
